PySulfSat/Cali_BW2022.pkl
PySulfSat/Cali_Blanchard2021.pkl
PySulfSat/Cali_ChowDas22.pkl
PySulfSat/Cali_Fortin2015.pkl
PySulfSat/Cali_LiZhang22.pkl
PySulfSat/Cali_Liu2021.pkl
PySulfSat/Cali_MK2015.pkl
PySulfSat/Cali_OM2022.pkl
PySulfSat/Cali_Smythe17.pkl
PySulfSat/Cali_ZT2019.pkl
PySulfSat/Smythe17.pkl
PySulfSat/__init__.py
PySulfSat/_version.py
PySulfSat/cali_plots.py
PySulfSat/core_calcs.py
PySulfSat/error_prop.py
PySulfSat/import_data.py
PySulfSat/mantle_melting.py
PySulfSat/monte_carlo_s_in_sulf_recon.py
PySulfSat/s6_corrections.py
PySulfSat/scas_calc.py
PySulfSat/scss_calcs2.py
PySulfSat/sulf_mass_balance.py
pysulfsat-1.0.11.dist-info/licenses/LICENSE.txt
pysulfsat-1.0.11.dist-info/METADATA
pysulfsat-1.0.11.dist-info/WHEEL
pysulfsat-1.0.11.dist-info/top_level.txt
pysulfsat-1.0.11.dist-info/RECORD
